quickBayes/__init__.py
quickBayes/log_likelihood.py
quickBayes/fitting/__init__.py
quickBayes/fitting/fit_engine.py
quickBayes/fitting/fit_utils.py
quickBayes/fitting/gofit_base.py
quickBayes/fitting/gofit_engine.py
quickBayes/fitting/scipy_engine.py
quickBayes/functions/BG.py
quickBayes/functions/SE.py
quickBayes/functions/SE_fix.py
quickBayes/functions/__init__.py
quickBayes/functions/base.py
quickBayes/functions/composite.py
quickBayes/functions/convolution.py
quickBayes/functions/delta.py
quickBayes/functions/exp_decay.py
quickBayes/functions/gaussian.py
quickBayes/functions/lorentz.py
quickBayes/functions/qe_function.py
quickBayes/functions/qldata_function.py
quickBayes/functions/qse_fixed.py
quickBayes/functions/qse_function.py
quickBayes/test_helpers/fitting_data.py
quickBayes/test_helpers/grid_template.py
quickBayes/test_helpers/model_selection.py
quickBayes/test_helpers/template_fit_test.py
quickBayes/test_helpers/template_scipy_fit.py
quickBayes/test_helpers/workflow_helper.py
quickBayes/utils/__init__.py
quickBayes/utils/crop_data.py
quickBayes/utils/general.py
quickBayes/utils/parallel.py
quickBayes/utils/spline.py
quickBayes/workflow/__init__.py
quickBayes/workflow/template.py
quickBayes/workflow/grid_search/__init__.py
quickBayes/workflow/grid_search/qse_grid_search.py
quickBayes/workflow/grid_search/template.py
quickBayes/workflow/model_selection/QSE.py
quickBayes/workflow/model_selection/QlData.py
quickBayes/workflow/model_selection/__init__.py
quickBayes/workflow/model_selection/muon_decay.py
quickBayes/workflow/model_selection/template.py
quickbayes-1.0.2.dist-info/METADATA
quickbayes-1.0.2.dist-info/WHEEL
quickbayes-1.0.2.dist-info/licenses/LICENSE
quickbayes-1.0.2.dist-info/RECORD
