Metadata-Version: 2.4
Name: quickBayes
Version: 1.0.2
Summary: A Bayesian fitting package used for model selection and grid searches of fits for neutron and muon data.
Project-URL: Homepage, https://quickbayes.readthedocs.io/en/latest/
Project-URL: Documentation, https://quickbayes.readthedocs.io/en/latest/
Project-URL: Repository, https://github.com/ISISNeutronMuon/quickBayes
Author-email: Anthony Lim <anthony.lim@stfc.ac.uk>
License: BSD
License-File: LICENSE
Keywords: QENS,bayesian,fitting,muons
Requires-Python: >=3.7.1
Requires-Dist: numpy
Requires-Dist: scipy
Provides-Extra: docs
Requires-Dist: jupyter-book; extra == 'docs'
Requires-Dist: nbsphinx==0.9.4; extra == 'docs'
Requires-Dist: sphinx==7.3.7; extra == 'docs'
Provides-Extra: gofit
Requires-Dist: eigen; extra == 'gofit'
Requires-Dist: gofit; extra == 'gofit'
Requires-Dist: pybind11[global]; extra == 'gofit'
